[
  {
    "page": 1,
    "pages": 1,
    "per_page": 20000,
    "total": 65,
    "sourceid": "2",
    "lastupdated": "2025-12-16"
  },
  [
    {
      "indicator": {
        "id": "NY.GDP.MKTP.KD.ZG",
        "value": "GDP growth (annual %)"
      },
      "country": {
        "id": "JP",
        "value": "Japan"
      },
      "countryiso3code": "JPN",
      "date": "2024",
      "value": 0.104309021773304,
      "unit": "",
      "obs_status": "",
      "decimal": 1
    },
    {
      "indicator": {
        "id": "NY.GDP.MKTP.KD.ZG",
        "value": "GDP growth (annual %)"
      },
      "country": {
        "id": "JP",
        "value": "Japan"
      },
      "countryiso3code": "JPN",
      "date": "2023",
      "value": 1.47503481053384,
      "unit": "",
      "obs_status": "",
      "decimal": 1
    },
    {
      "indicator": {
        "id": "NY.GDP.MKTP.KD.ZG",
        "value": "GDP growth (annual %)"
      },
      "country": {
        "id": "JP",
        "value": "Japan"
      },
      "countryiso3code": "JPN",
      "date": "2022",
      "value": 0.941998775483285,
      "unit": "",
      "obs_status": "",
      "decimal": 1
    },
    {
      "indicator": {
        "id": "NY.GDP.MKTP.KD.ZG",
        "value": "GDP growth (annual %)"
      },
      "country": {
        "id": "JP",
        "value": "Japan"
      },
      "countryiso3code": "JPN",
      "date": "2021",
      "value": 2.69657404187188,
      "unit": "",
      "obs_status": "",
      "decimal": 1
    },
    {
      "indicator": {
        "id": "NY.GDP.MKTP.KD.ZG",
        "value": "GDP growth (annual %)"
      },
      "country": {
        "id": "JP",
        "value": "Japan"
      },
      "countryiso3code": "JPN",
      "date": "2020",
      "value": -4.16876457146743,
      "unit": "",
      "obs_status": "",
      "decimal": 1
    },
    {
      "indicator": {
        "id": "NY.GDP.MKTP.KD.ZG",
        "value": "GDP growth (annual %)"
      },
      "country": {
        "id": "JP",
        "value": "Japan"
      },
      "countryiso3code": "JPN",
      "date": "2019",
      "value": -0.402169200894946,
      "unit": "",
      "obs_status": "",
      "decimal": 1
    },
    {
      "indicator": {
        "id": "NY.GDP.MKTP.KD.ZG",
        "value": "GDP growth (annual %)"
      },
      "country": {
        "id": "JP",
        "value": "Japan"
      },
      "countryiso3code": "JPN",
      "date": "2018",
      "value": 0.643391023533141,
      "unit": "",
      "obs_status": "",
      "decimal": 1
    },
    {
      "indicator": {
        "id": "NY.GDP.MKTP.KD.ZG",
        "value": "GDP growth (annual %)"
      },
      "country": {
        "id": "JP",
        "value": "Japan"
      },
      "countryiso3code": "JPN",
      "date": "2017",
      "value": 1.67533175173359,
      "unit": "",
      "obs_status": "",
      "decimal": 1
    },
    {
      "indicator": {
        "id": "NY.GDP.MKTP.KD.ZG",
        "value": "GDP growth (annual %)"
      },
      "country": {
        "id": "JP",
        "value": "Japan"
      },
      "countryiso3code": "JPN",
      "date": "2016",
      "value": 0.753826745789127,
      "unit": "",
      "obs_status": "",
      "decimal": 1
    },
    {
      "indicator": {
        "id": "NY.GDP.MKTP.KD.ZG",
        "value": "GDP growth (annual %)"
      },
      "country": {
        "id": "JP",
        "value": "Japan"
      },
      "countryiso3code": "JPN",
      "date": "2015",
      "value": 1.56062669680782,
      "unit": "",
      "obs_status": "",
      "decimal": 1
    },
    {
      "indicator": {
        "id": "NY.GDP.MKTP.KD.ZG",
        "value": "GDP growth (annual %)"
      },
      "country": {
        "id": "JP",
        "value": "Japan"
      },
      "countryiso3code": "JPN",
      "date": "2014",
      "value": 0.296205514141889,
      "unit": "",
      "obs_status": "",
      "decimal": 1
    },
    {
      "indicator": {
        "id": "NY.GDP.MKTP.KD.ZG",
        "value": "GDP growth (annual %)"
      },
      "country": {
        "id": "JP",
        "value": "Japan"
      },
      "countryiso3code": "JPN",
      "date": "2013",
      "value": 2.00510017681211,
      "unit": "",
      "obs_status": "",
      "decimal": 1
    },
    {
      "indicator": {
        "id": "NY.GDP.MKTP.KD.ZG",
        "value": "GDP growth (annual %)"
      },
      "country": {
        "id": "JP",
        "value": "Japan"
      },
      "countryiso3code": "JPN",
      "date": "2012",
      "value": 1.37475099905274,
      "unit": "",
      "obs_status": "",
      "decimal": 1
    },
    {
      "indicator": {
        "id": "NY.GDP.MKTP.KD.ZG",
        "value": "GDP growth (annual %)"
      },
      "country": {
        "id": "JP",
        "value": "Japan"
      },
      "countryiso3code": "JPN",
      "date": "2011",
      "value": 0.0238095237995424,
      "unit": "",
      "obs_status": "",
      "decimal": 1
    },
    {
      "indicator": {
        "id": "NY.GDP.MKTP.KD.ZG",
        "value": "GDP growth (annual %)"
      },
      "country": {
        "id": "JP",
        "value": "Japan"
      },
      "countryiso3code": "JPN",
      "date": "2010",
      "value": 4.09791791943181,
      "unit": "",
      "obs_status": "",
      "decimal": 1
    },
    {
      "indicator": {
        "id": "NY.GDP.MKTP.KD.ZG",
        "value": "GDP growth (annual %)"
      },
      "country": {
        "id": "JP",
        "value": "Japan"
      },
      "countryiso3code": "JPN",
      "date": "2009",
      "value": -5.69323635892741,
      "unit": "",
      "obs_status": "",
      "decimal": 1
    },
    {
      "indicator": {
        "id": "NY.GDP.MKTP.KD.ZG",
        "value": "GDP growth (annual %)"
      },
      "country": {
        "id": "JP",
        "value": "Japan"
      },
      "countryiso3code": "JPN",
      "date": "2008",
      "value": -1.22428900061713,
      "unit": "",
      "obs_status": "",
      "decimal": 1
    },
    {
      "indicator": {
        "id": "NY.GDP.MKTP.KD.ZG",
        "value": "GDP growth (annual %)"
      },
      "country": {
        "id": "JP",
        "value": "Japan"
      },
      "countryiso3code": "JPN",
      "date": "2007",
      "value": 1.48396941157472,
      "unit": "",
      "obs_status": "",
      "decimal": 1
    },
    {
      "indicator": {
        "id": "NY.GDP.MKTP.KD.ZG",
        "value": "GDP growth (annual %)"
      },
      "country": {
        "id": "JP",
        "value": "Japan"
      },
      "countryiso3code": "JPN",
      "date": "2006",
      "value": 1.3723501275831,
      "unit": "",
      "obs_status": "",
      "decimal": 1
    },
    {
      "indicator": {
        "id": "NY.GDP.MKTP.KD.ZG",
        "value": "GDP growth (annual %)"
      },
      "country": {
        "id": "JP",
        "value": "Japan"
      },
      "countryiso3code": "JPN",
      "date": "2005",
      "value": 1.80390087215821,
      "unit": "",
      "obs_status": "",
      "decimal": 1
    },
    {
      "indicator": {
        "id": "NY.GDP.MKTP.KD.ZG",
        "value": "GDP growth (annual %)"
      },
      "country": {
        "id": "JP",
        "value": "Japan"
      },
      "countryiso3code": "JPN",
      "date": "2004",
      "value": 2.18611569439318,
      "unit": "",
      "obs_status": "",
      "decimal": 1
    },
    {
      "indicator": {
        "id": "NY.GDP.MKTP.KD.ZG",
        "value": "GDP growth (annual %)"
      },
      "country": {
        "id": "JP",
        "value": "Japan"
      },
      "countryiso3code": "JPN",
      "date": "2003",
      "value": 1.53512549946694,
      "unit": "",
      "obs_status": "",
      "decimal": 1
    },
    {
      "indicator": {
        "id": "NY.GDP.MKTP.KD.ZG",
        "value": "GDP growth (annual %)"
      },
      "country": {
        "id": "JP",
        "value": "Japan"
      },
      "countryiso3code": "JPN",
      "date": "2002",
      "value": 0.0419624992862282,
      "unit": "",
      "obs_status": "",
      "decimal": 1
    },
    {
      "indicator": {
        "id": "NY.GDP.MKTP.KD.ZG",
        "value": "GDP growth (annual %)"
      },
      "country": {
        "id": "JP",
        "value": "Japan"
      },
      "countryiso3code": "JPN",
      "date": "2001",
      "value": 0.386103426142029,
      "unit": "",
      "obs_status": "",
      "decimal": 1
    },
    {
      "indicator": {
        "id": "NY.GDP.MKTP.KD.ZG",
        "value": "GDP growth (annual %)"
      },
      "country": {
        "id": "JP",
        "value": "Japan"
      },
      "countryiso3code": "JPN",
      "date": "2000",
      "value": 2.76464755136783,
      "unit": "",
      "obs_status": "",
      "decimal": 1
    },
    {
      "indicator": {
        "id": "NY.GDP.MKTP.KD.ZG",
        "value": "GDP growth (annual %)"
      },
      "country": {
        "id": "JP",
        "value": "Japan"
      },
      "countryiso3code": "JPN",
      "date": "1999",
      "value": -0.333929957687772,
      "unit": "",
      "obs_status": "",
      "decimal": 1
    },
    {
      "indicator": {
        "id": "NY.GDP.MKTP.KD.ZG",
        "value": "GDP growth (annual %)"
      },
      "country": {
        "id": "JP",
        "value": "Japan"
      },
      "countryiso3code": "JPN",
      "date": "1998",
      "value": -1.27033049466078,
      "unit": "",
      "obs_status": "",
      "decimal": 1
    },
    {
      "indicator": {
        "id": "NY.GDP.MKTP.KD.ZG",
        "value": "GDP growth (annual %)"
      },
      "country": {
        "id": "JP",
        "value": "Japan"
      },
      "countryiso3code": "JPN",
      "date": "1997",
      "value": 0.981228732290873,
      "unit": "",
      "obs_status": "",
      "decimal": 1
    },
    {
      "indicator": {
        "id": "NY.GDP.MKTP.KD.ZG",
        "value": "GDP growth (annual %)"
      },
      "country": {
        "id": "JP",
        "value": "Japan"
      },
      "countryiso3code": "JPN",
      "date": "1996",
      "value": 3.13387099272759,
      "unit": "",
      "obs_status": "",
      "decimal": 1
    },
    {
      "indicator": {
        "id": "NY.GDP.MKTP.KD.ZG",
        "value": "GDP growth (annual %)"
      },
      "country": {
        "id": "JP",
        "value": "Japan"
      },
      "countryiso3code": "JPN",
      "date": "1995",
      "value": 2.6309996164206,
      "unit": "",
      "obs_status": "",
      "decimal": 1
    },
    {
      "indicator": {
        "id": "NY.GDP.MKTP.KD.ZG",
        "value": "GDP growth (annual %)"
      },
      "country": {
        "id": "JP",
        "value": "Japan"
      },
      "countryiso3code": "JPN",
      "date": "1994",
      "value": 1.0833831743207,
      "unit": "",
      "obs_status": "",
      "decimal": 1
    },
    {
      "indicator": {
        "id": "NY.GDP.MKTP.KD.ZG",
        "value": "GDP growth (annual %)"
      },
      "country": {
        "id": "JP",
        "value": "Japan"
      },
      "countryiso3code": "JPN",
      "date": "1993",
      "value": -0.459219716250544,
      "unit": "",
      "obs_status": "",
      "decimal": 1
    },
    {
      "indicator": {
        "id": "NY.GDP.MKTP.KD.ZG",
        "value": "GDP growth (annual %)"
      },
      "country": {
        "id": "JP",
        "value": "Japan"
      },
      "countryiso3code": "JPN",
      "date": "1992",
      "value": 0.900586066438109,
      "unit": "",
      "obs_status": "",
      "decimal": 1
    },
    {
      "indicator": {
        "id": "NY.GDP.MKTP.KD.ZG",
        "value": "GDP growth (annual %)"
      },
      "country": {
        "id": "JP",
        "value": "Japan"
      },
      "countryiso3code": "JPN",
      "date": "1991",
      "value": 3.52335723553459,
      "unit": "",
      "obs_status": "",
      "decimal": 1
    },
    {
      "indicator": {
        "id": "NY.GDP.MKTP.KD.ZG",
        "value": "GDP growth (annual %)"
      },
      "country": {
        "id": "JP",
        "value": "Japan"
      },
      "countryiso3code": "JPN",
      "date": "1990",
      "value": 4.84092905699353,
      "unit": "",
      "obs_status": "",
      "decimal": 1
    },
    {
      "indicator": {
        "id": "NY.GDP.MKTP.KD.ZG",
        "value": "GDP growth (annual %)"
      },
      "country": {
        "id": "JP",
        "value": "Japan"
      },
      "countryiso3code": "JPN",
      "date": "1989",
      "value": 4.92578541317788,
      "unit": "",
      "obs_status": "",
      "decimal": 1
    },
    {
      "indicator": {
        "id": "NY.GDP.MKTP.KD.ZG",
        "value": "GDP growth (annual %)"
      },
      "country": {
        "id": "JP",
        "value": "Japan"
      },
      "countryiso3code": "JPN",
      "date": "1988",
      "value": 6.66163652210332,
      "unit": "",
      "obs_status": "",
      "decimal": 1
    },
    {
      "indicator": {
        "id": "NY.GDP.MKTP.KD.ZG",
        "value": "GDP growth (annual %)"
      },
      "country": {
        "id": "JP",
        "value": "Japan"
      },
      "countryiso3code": "JPN",
      "date": "1987",
      "value": 4.64886139743521,
      "unit": "",
      "obs_status": "",
      "decimal": 1
    },
    {
      "indicator": {
        "id": "NY.GDP.MKTP.KD.ZG",
        "value": "GDP growth (annual %)"
      },
      "country": {
        "id": "JP",
        "value": "Japan"
      },
      "countryiso3code": "JPN",
      "date": "1986",
      "value": 3.29404761349421,
      "unit": "",
      "obs_status": "",
      "decimal": 1
    },
    {
      "indicator": {
        "id": "NY.GDP.MKTP.KD.ZG",
        "value": "GDP growth (annual %)"
      },
      "country": {
        "id": "JP",
        "value": "Japan"
      },
      "countryiso3code": "JPN",
      "date": "1985",
      "value": 5.15980790450274,
      "unit": "",
      "obs_status": "",
      "decimal": 1
    },
    {
      "indicator": {
        "id": "NY.GDP.MKTP.KD.ZG",
        "value": "GDP growth (annual %)"
      },
      "country": {
        "id": "JP",
        "value": "Japan"
      },
      "countryiso3code": "JPN",
      "date": "1984",
      "value": 4.41088015355157,
      "unit": "",
      "obs_status": "",
      "decimal": 1
    },
    {
      "indicator": {
        "id": "NY.GDP.MKTP.KD.ZG",
        "value": "GDP growth (annual %)"
      },
      "country": {
        "id": "JP",
        "value": "Japan"
      },
      "countryiso3code": "JPN",
      "date": "1983",
      "value": 3.63019857277,
      "unit": "",
      "obs_status": "",
      "decimal": 1
    },
    {
      "indicator": {
        "id": "NY.GDP.MKTP.KD.ZG",
        "value": "GDP growth (annual %)"
      },
      "country": {
        "id": "JP",
        "value": "Japan"
      },
      "countryiso3code": "JPN",
      "date": "1982",
      "value": 3.27974274279195,
      "unit": "",
      "obs_status": "",
      "decimal": 1
    },
    {
      "indicator": {
        "id": "NY.GDP.MKTP.KD.ZG",
        "value": "GDP growth (annual %)"
      },
      "country": {
        "id": "JP",
        "value": "Japan"
      },
      "countryiso3code": "JPN",
      "date": "1981",
      "value": 4.26062449361741,
      "unit": "",
      "obs_status": "",
      "decimal": 1
    },
    {
      "indicator": {
        "id": "NY.GDP.MKTP.KD.ZG",
        "value": "GDP growth (annual %)"
      },
      "country": {
        "id": "JP",
        "value": "Japan"
      },
      "countryiso3code": "JPN",
      "date": "1980",
      "value": 2.81759120759222,
      "unit": "",
      "obs_status": "",
      "decimal": 1
    },
    {
      "indicator": {
        "id": "NY.GDP.MKTP.KD.ZG",
        "value": "GDP growth (annual %)"
      },
      "country": {
        "id": "JP",
        "value": "Japan"
      },
      "countryiso3code": "JPN",
      "date": "1979",
      "value": 5.48404183215798,
      "unit": "",
      "obs_status": "",
      "decimal": 1
    },
    {
      "indicator": {
        "id": "NY.GDP.MKTP.KD.ZG",
        "value": "GDP growth (annual %)"
      },
      "country": {
        "id": "JP",
        "value": "Japan"
      },
      "countryiso3code": "JPN",
      "date": "1978",
      "value": 5.2719415031039,
      "unit": "",
      "obs_status": "",
      "decimal": 1
    },
    {
      "indicator": {
        "id": "NY.GDP.MKTP.KD.ZG",
        "value": "GDP growth (annual %)"
      },
      "country": {
        "id": "JP",
        "value": "Japan"
      },
      "countryiso3code": "JPN",
      "date": "1977",
      "value": 4.39033795035795,
      "unit": "",
      "obs_status": "",
      "decimal": 1
    },
    {
      "indicator": {
        "id": "NY.GDP.MKTP.KD.ZG",
        "value": "GDP growth (annual %)"
      },
      "country": {
        "id": "JP",
        "value": "Japan"
      },
      "countryiso3code": "JPN",
      "date": "1976",
      "value": 3.97498409081336,
      "unit": "",
      "obs_status": "",
      "decimal": 1
    },
    {
      "indicator": {
        "id": "NY.GDP.MKTP.KD.ZG",
        "value": "GDP growth (annual %)"
      },
      "country": {
        "id": "JP",
        "value": "Japan"
      },
      "countryiso3code": "JPN",
      "date": "1975",
      "value": 3.09157591647113,
      "unit": "",
      "obs_status": "",
      "decimal": 1
    },
    {
      "indicator": {
        "id": "NY.GDP.MKTP.KD.ZG",
        "value": "GDP growth (annual %)"
      },
      "country": {
        "id": "JP",
        "value": "Japan"
      },
      "countryiso3code": "JPN",
      "date": "1974",
      "value": -1.22523982783679,
      "unit": "",
      "obs_status": "",
      "decimal": 1
    },
    {
      "indicator": {
        "id": "NY.GDP.MKTP.KD.ZG",
        "value": "GDP growth (annual %)"
      },
      "country": {
        "id": "JP",
        "value": "Japan"
      },
      "countryiso3code": "JPN",
      "date": "1973",
      "value": 8.03259997458163,
      "unit": "",
      "obs_status": "",
      "decimal": 1
    },
    {
      "indicator": {
        "id": "NY.GDP.MKTP.KD.ZG",
        "value": "GDP growth (annual %)"
      },
      "country": {
        "id": "JP",
        "value": "Japan"
      },
      "countryiso3code": "JPN",
      "date": "1972",
      "value": 8.41354725566508,
      "unit": "",
      "obs_status": "",
      "decimal": 1
    },
    {
      "indicator": {
        "id": "NY.GDP.MKTP.KD.ZG",
        "value": "GDP growth (annual %)"
      },
      "country": {
        "id": "JP",
        "value": "Japan"
      },
      "countryiso3code": "JPN",
      "date": "1971",
      "value": 4.6989920420522,
      "unit": "",
      "obs_status": "",
      "decimal": 1
    },
    {
      "indicator": {
        "id": "NY.GDP.MKTP.KD.ZG",
        "value": "GDP growth (annual %)"
      },
      "country": {
        "id": "JP",
        "value": "Japan"
      },
      "countryiso3code": "JPN",
      "date": "1970",
      "value": 0.399050644662367,
      "unit": "",
      "obs_status": "",
      "decimal": 1
    },
    {
      "indicator": {
        "id": "NY.GDP.MKTP.KD.ZG",
        "value": "GDP growth (annual %)"
      },
      "country": {
        "id": "JP",
        "value": "Japan"
      },
      "countryiso3code": "JPN",
      "date": "1969",
      "value": 12.4778945144981,
      "unit": "",
      "obs_status": "",
      "decimal": 1
    },
    {
      "indicator": {
        "id": "NY.GDP.MKTP.KD.ZG",
        "value": "GDP growth (annual %)"
      },
      "country": {
        "id": "JP",
        "value": "Japan"
      },
      "countryiso3code": "JPN",
      "date": "1968",
      "value": 12.8824681383231,
      "unit": "",
      "obs_status": "",
      "decimal": 1
    },
    {
      "indicator": {
        "id": "NY.GDP.MKTP.KD.ZG",
        "value": "GDP growth (annual %)"
      },
      "country": {
        "id": "JP",
        "value": "Japan"
      },
      "countryiso3code": "JPN",
      "date": "1967",
      "value": 11.0821423246932,
      "unit": "",
      "obs_status": "",
      "decimal": 1
    },
    {
      "indicator": {
        "id": "NY.GDP.MKTP.KD.ZG",
        "value": "GDP growth (annual %)"
      },
      "country": {
        "id": "JP",
        "value": "Japan"
      },
      "countryiso3code": "JPN",
      "date": "1966",
      "value": 10.6385615591631,
      "unit": "",
      "obs_status": "",
      "decimal": 1
    },
    {
      "indicator": {
        "id": "NY.GDP.MKTP.KD.ZG",
        "value": "GDP growth (annual %)"
      },
      "country": {
        "id": "JP",
        "value": "Japan"
      },
      "countryiso3code": "JPN",
      "date": "1965",
      "value": 5.81970787298197,
      "unit": "",
      "obs_status": "",
      "decimal": 1
    },
    {
      "indicator": {
        "id": "NY.GDP.MKTP.KD.ZG",
        "value": "GDP growth (annual %)"
      },
      "country": {
        "id": "JP",
        "value": "Japan"
      },
      "countryiso3code": "JPN",
      "date": "1964",
      "value": 11.676708196398,
      "unit": "",
      "obs_status": "",
      "decimal": 1
    },
    {
      "indicator": {
        "id": "NY.GDP.MKTP.KD.ZG",
        "value": "GDP growth (annual %)"
      },
      "country": {
        "id": "JP",
        "value": "Japan"
      },
      "countryiso3code": "JPN",
      "date": "1963",
      "value": 8.473642382794,
      "unit": "",
      "obs_status": "",
      "decimal": 1
    },
    {
      "indicator": {
        "id": "NY.GDP.MKTP.KD.ZG",
        "value": "GDP growth (annual %)"
      },
      "country": {
        "id": "JP",
        "value": "Japan"
      },
      "countryiso3code": "JPN",
      "date": "1962",
      "value": 8.90897299558067,
      "unit": "",
      "obs_status": "",
      "decimal": 1
    },
    {
      "indicator": {
        "id": "NY.GDP.MKTP.KD.ZG",
        "value": "GDP growth (annual %)"
      },
      "country": {
        "id": "JP",
        "value": "Japan"
      },
      "countryiso3code": "JPN",
      "date": "1961",
      "value": 12.0435364080117,
      "unit": "",
      "obs_status": "",
      "decimal": 1
    },
    {
      "indicator": {
        "id": "NY.GDP.MKTP.KD.ZG",
        "value": "GDP growth (annual %)"
      },
      "country": {
        "id": "JP",
        "value": "Japan"
      },
      "countryiso3code": "JPN",
      "date": "1960",
      "value": null,
      "unit": "",
      "obs_status": "",
      "decimal": 1
    }
  ]
]